streamlit_pagnation/__init__.py
streamlit_pagnation/frontend/build/asset-manifest.json
streamlit_pagnation/frontend/build/bootstrap.min.css
streamlit_pagnation/frontend/build/index.html
streamlit_pagnation/frontend/build/precache-manifest.43bb459d0959ee104ce8f6b3d63a4806.js
streamlit_pagnation/frontend/build/precache-manifest.ccfe45cbd33f5f7cd344f7605d8ca472.js
streamlit_pagnation/frontend/build/service-worker.js
streamlit_pagnation/frontend/build/static/css/main.004acf31.chunk.css
streamlit_pagnation/frontend/build/static/css/main.004acf31.chunk.css.map
streamlit_pagnation/frontend/build/static/css/main.ccd4e4ae.chunk.css
streamlit_pagnation/frontend/build/static/css/main.ccd4e4ae.chunk.css.map
streamlit_pagnation/frontend/build/static/js/2.cbebb380.chunk.js
streamlit_pagnation/frontend/build/static/js/2.cbebb380.chunk.js.LICENSE.txt
streamlit_pagnation/frontend/build/static/js/2.cbebb380.chunk.js.map
streamlit_pagnation/frontend/build/static/js/main.3ac2dffb.chunk.js
streamlit_pagnation/frontend/build/static/js/main.3ac2dffb.chunk.js.map
streamlit_pagnation/frontend/build/static/js/main.acfd91d8.chunk.js
streamlit_pagnation/frontend/build/static/js/main.acfd91d8.chunk.js.map
streamlit_pagnation/frontend/build/static/js/runtime-main.1367036c.js
streamlit_pagnation/frontend/build/static/js/runtime-main.1367036c.js.map
streamlit_pagnation-0.0.2.dist-info/LICENSE
streamlit_pagnation-0.0.2.dist-info/METADATA
streamlit_pagnation-0.0.2.dist-info/WHEEL
streamlit_pagnation-0.0.2.dist-info/top_level.txt
streamlit_pagnation-0.0.2.dist-info/RECORD
